setup.py
authy/__init__.py
authy.egg-info/PKG-INFO
authy.egg-info/SOURCES.txt
authy.egg-info/dependency_links.txt
authy.egg-info/requires.txt
authy.egg-info/top_level.txt
authy/api/__init__.py
authy/api/resources.py
authy/contrib/__init__.py
tests/__init__.py
tests/test_client.py
tests/test_helper.py
tests/test_one_touch.py
tests/test_phones.py
tests/test_tokens.py
tests/test_users.py