Metadata-Version: 1.1
Name: authy
Version: 2.1.5
Summary: Authy API Client
Home-page: http://github.com/authy/authy-python
Author: Authy Inc
Author-email: dev-support@authy.com
License: UNKNOWN
Keywords: authy,two factor,authentication
Platform: UNKNOWN
Classifier: Development Status :: 5 - Production/Stable
Classifier: Intended Audience :: Developers
Classifier: License :: OSI Approved :: MIT License
Classifier: Operating System :: OS Independent
Classifier: Programming Language :: Python
Classifier: Programming Language :: Python :: 2.5
Classifier: Programming Language :: Python :: 2.6
Classifier: Programming Language :: Python :: 2.7
Classifier: Topic :: Software Development :: Libraries :: Python Modules
Classifier: Topic :: Security
